<?xml version="1.0" encoding="UTF-8" standalone="yes"?>
<contentHaul xmlns:a="http://www.appian.com/ae/types/2009">
    <rule>
        <name>LDAP_configureLDAPTestResultRow</name>
        <uuid>_a-0000db98-7620-8000-5130-010000010000_2516</uuid>
        <description></description>
        <parentUuid>_a-0000d62a-9e0e-8000-ac7a-680000680000_7543</parentUuid>
        <visibility>
            <advertise>false</advertise>
            <hierarchy>true</hierarchy>
            <indexable>true</indexable>
            <quota>false</quota>
            <searchable>true</searchable>
            <system>false</system>
            <unlogged>false</unlogged>
        </visibility>
        <definition>#&quot;SYSTEM_SYSRULES_gridTextColumn&quot;(&#xD;
  label: ri!label,&#xD;
  field: ri!field,&#xD;
  data: apply(&#xD;
    fn!tostring,&#xD;
    index(ri!results, ri!field, &quot;&quot;)&#xD;
  )&#xD;
)</definition>
        <namedTypedValue>
            <name>index</name>
            <type>
                <name>int</name>
                <namespace>http://www.w3.org/2001/XMLSchema</namespace>
            </type>
        </namedTypedValue>
        <namedTypedValue>
            <name>label</name>
            <type>
                <name>string</name>
                <namespace>http://www.w3.org/2001/XMLSchema</namespace>
            </type>
            <value/>
        </namedTypedValue>
        <namedTypedValue>
            <name>field</name>
            <type>
                <name>string</name>
                <namespace>http://www.w3.org/2001/XMLSchema</namespace>
            </type>
            <value/>
        </namedTypedValue>
        <namedTypedValue>
            <name>results</name>
            <type>
                <name>Variant</name>
                <namespace>http://www.appian.com/ae/types/2009</namespace>
            </type>
        </namedTypedValue>
        <preferredEditor>legacy</preferredEditor>
        <offlineEnabled>false</offlineEnabled>
    </rule>
    <roleMap public="true">
        <role allowForAll="false" inherit="true" name="readers">
            <users/>
            <groups/>
        </role>
        <role allowForAll="false" inherit="true" name="authors">
            <users/>
            <groups/>
        </role>
        <role allowForAll="false" inherit="true" name="administrators">
            <users/>
            <groups/>
        </role>
        <role allowForAll="false" inherit="false" name="denyReaders">
            <users/>
            <groups/>
        </role>
        <role allowForAll="false" inherit="false" name="denyAuthors">
            <users/>
            <groups/>
        </role>
        <role allowForAll="false" inherit="false" name="denyAdministrators">
            <users/>
            <groups/>
        </role>
    </roleMap>
    <typedValue>
        <type>
            <name>RuleTestConfig</name>
            <namespace>http://www.appian.com/ae/types/2009</namespace>
        </type>
        <value>
            <a:ruleInputTestConfigs>
                <a:value xmlns:xsd="http://www.w3.org/2001/XMLSchema" xmlns:xsi="http://www.w3.org/2001/XMLSchema-instance" xsi:type="xsd:string"/>
                <a:nameRef>index</a:nameRef>
            </a:ruleInputTestConfigs>
            <a:ruleInputTestConfigs>
                <a:value xmlns:xsi="http://www.w3.org/2001/XMLSchema-instance" xsi:nil="true"/>
                <a:nameRef>label</a:nameRef>
            </a:ruleInputTestConfigs>
            <a:ruleInputTestConfigs>
                <a:value xmlns:xsi="http://www.w3.org/2001/XMLSchema-instance" xsi:nil="true"/>
                <a:nameRef>field</a:nameRef>
            </a:ruleInputTestConfigs>
            <a:ruleInputTestConfigs>
                <a:value xmlns:xsd="http://www.w3.org/2001/XMLSchema" xmlns:xsi="http://www.w3.org/2001/XMLSchema-instance" xsi:type="xsd:string"/>
                <a:nameRef>results</a:nameRef>
            </a:ruleInputTestConfigs>
        </value>
    </typedValue>
</contentHaul>
